[
    {
        "src": "https://www.youtube.com/embed/lQ5pw0SrJd4"
    },
    {
        "src": "https://www.youtube.com/embed/RIerTVDKmpk"
    },
    {
        "src": "https://www.youtube.com/embed/1_VpFGvxC0M"
    },
    {
        "src": "https://www.youtube.com/embed/Sf9d3XYZsdg"
    },
    {
        "src": "https://www.youtube.com/embed/lpPPs5kGOMQ"
    },
    {
        "src": "https://www.youtube.com/embed/2uIFY8Sxo0M"
    },
    {
        "src": "https://www.youtube.com/embed/dQAxAtgNYDg"
    },
    {
        "src": "https://www.youtube.com/embed/br-Y92QUGP0"
    },
    {
        "src": "https://www.youtube.com/embed/5klqQqU19vM"
    },
    {
        "src": "https://www.youtube.com/embed/2ekdtN8v_aE"
    },
    {
        "src": "https://www.youtube.com/embed/AfqgyAhRch4"
    },
    {
        "src": "https://www.youtube.com/embed/19o3Ml6Ek_0"
    },
    {
        "src": "https://www.youtube.com/embed/O6ZvhVkzQxY"
    },
    {
        "src": "https://www.youtube.com/embed/bzRaGRI0wzk"
    }
]